MANIFEST.in
README.rst
setup.py
firm/__init__.py
firm/base.py
firm/bitfields.py
firm/debug_info.py
firm/entity.py
firm/extras.py
firm/function.py
firm/initializer.py
firm/memorypolicy.py
firm/node.py
firm/operations.py
firm/tarval.py
firm/types.py
firm/wrap.py
firm/tests/__init__.py
firm/tests/test_entity.py
firm/tests/test_initializer.py
firm/tests/test_simple.py
firm/tests/test_tarval.py
firm/tests/test_types.py
gen/__init__.py
gen/compile.py
gen/firmtypes.h
gen/node_defs.h
gen/subbuild.py
gen/symbols/callbacks.h
gen/symbols/debug_info.h
gen/symbols/entity.h
gen/symbols/extras.h
gen/symbols/function.h
gen/symbols/initializer.h
gen/symbols/node.h
gen/symbols/program.h
gen/symbols/tarval.h
gen/symbols/types.h
libfirm/COPYING
libfirm/Makefile
libfirm/NEWS.md
libfirm/README.md
libfirm/include/libfirm/analyze_irg_args.h
libfirm/include/libfirm/be.h
libfirm/include/libfirm/begin.h
libfirm/include/libfirm/callgraph.h
libfirm/include/libfirm/cdep.h
libfirm/include/libfirm/cgana.h
libfirm/include/libfirm/dbginfo.h
libfirm/include/libfirm/end.h
libfirm/include/libfirm/execfreq.h
libfirm/include/libfirm/firm.h
libfirm/include/libfirm/firm_common.h
libfirm/include/libfirm/firm_types.h
libfirm/include/libfirm/heights.h
libfirm/include/libfirm/ident.h
libfirm/include/libfirm/irarch.h
libfirm/include/libfirm/ircgopt.h
libfirm/include/libfirm/ircons.h
libfirm/include/libfirm/irconsconfirm.h
libfirm/include/libfirm/irdom.h
libfirm/include/libfirm/irdump.h
libfirm/include/libfirm/iredgekinds.h
libfirm/include/libfirm/iredges.h
libfirm/include/libfirm/irflag.h
libfirm/include/libfirm/irgmod.h
libfirm/include/libfirm/irgopt.h
libfirm/include/libfirm/irgraph.h
libfirm/include/libfirm/irgwalk.h
libfirm/include/libfirm/irio.h
libfirm/include/libfirm/irloop.h
libfirm/include/libfirm/irmemory.h
libfirm/include/libfirm/irmode.h
libfirm/include/libfirm/irnode.h
libfirm/include/libfirm/irop.h
libfirm/include/libfirm/iropt.h
libfirm/include/libfirm/iroptimize.h
python_firm.egg-info/PKG-INFO
python_firm.egg-info/SOURCES.txt
python_firm.egg-info/dependency_links.txt
python_firm.egg-info/requires.txt
python_firm.egg-info/top_level.txt