Metadata-Version: 1.1
Name: python-firm
Version: 0.1.4
Summary: FIRM Optimising Compiler Backend
Home-page: https://bitbucket.org/william_ml_leslie/python-firm
Author: William ML Leslie
Author-email: william.leslie.ttg@gmail.com
License: LGPL v2.1
Platform: UNKNOWN
Classifier: Development Status :: 2 - Pre-Alpha
Classifier: License :: OSI Approved :: GNU Lesser General Public License v2 or later (LGPLv2+)
Classifier: Programming Language :: Python :: 2
Classifier: Programming Language :: Python :: 2.7
Classifier: Programming Language :: Python :: 3
Classifier: Programming Language :: Python :: 3.5
Classifier: Topic :: Software Development :: Compilers
